Metadata-Version: 1.0
Name: ppm-telegram-bot-client
Version: 0.1.3
Summary: PPM Telegram Bot
Home-page: UNKNOWN
Author: UNKNOWN
Author-email: UNKNOWN
License: UNKNOWN
Keywords: Swagger,PPM Telegram Bot
Platform: UNKNOWN
